{
    "brand": "SPA",
    "home": {
        "menuItem": "Home",
        "h1": "Welcome to MPA/CSR demo",
        "h2": "Title 2 of home page"
    },
    "profile": {
        "menuItem": "Profile",
        "h1": "Create profile",
        "email": "Email address",
        "firstName": "First name",
        "lastName": "Last name",
        "trainer": "I am a trainer",
        "submit": "Create"
    },
    "signIn": {
        "menuItem": "Sign-in",
        "h1": "Sign-in"
    },
    "about": {
        "menuItem": "About",
        "h1": "About",
        "h2": "Title 2 of about page"
    },
    "notFound": {
        "h1": "404 NOT FOUND"
    }
}